{
    "fecha_publicacion": "2025-11-16",
    "PVPC": [
        {
            "hora": "00,00",
            "precio": 0.09774
        },
        {
            "hora": "01,00",
            "precio": 0.09276000000000001
        },
        {
            "hora": "02,00",
            "precio": 0.09173
        },
        {
            "hora": "03,00",
            "precio": 0.0897
        },
        {
            "hora": "04,00",
            "precio": 0.08853
        },
        {
            "hora": "05,00",
            "precio": 0.08841
        },
        {
            "hora": "06,00",
            "precio": 0.08806
        },
        {
            "hora": "07,00",
            "precio": 0.09564
        },
        {
            "hora": "08,00",
            "precio": 0.09484000000000001
        },
        {
            "hora": "09,00",
            "precio": 0.08012999999999999
        },
        {
            "hora": "10,00",
            "precio": 0.06334000000000001
        },
        {
            "hora": "11,00",
            "precio": 0.05919
        },
        {
            "hora": "12,00",
            "precio": 0.06252
        },
        {
            "hora": "13,00",
            "precio": 0.06173
        },
        {
            "hora": "14,00",
            "precio": 0.06153
        },
        {
            "hora": "15,00",
            "precio": 0.06581999999999999
        },
        {
            "hora": "16,00",
            "precio": 0.08476
        },
        {
            "hora": "17,00",
            "precio": 0.12015
        },
        {
            "hora": "18,00",
            "precio": 0.1345
        },
        {
            "hora": "19,00",
            "precio": 0.1446
        },
        {
            "hora": "20,00",
            "precio": 0.15359
        },
        {
            "hora": "21,00",
            "precio": 0.15721000000000002
        },
        {
            "hora": "22,00",
            "precio": 0.13882
        },
        {
            "hora": "23,00",
            "precio": 0.12348999999999999
        }
    ]
}