{
    "fecha_publicacion": "2026-05-16",
    "PVPC": [
        {
            "hora": "00,00",
            "precio": 0.12731
        },
        {
            "hora": "01,00",
            "precio": 0.1212
        },
        {
            "hora": "02,00",
            "precio": 0.12284
        },
        {
            "hora": "03,00",
            "precio": 0.12254000000000001
        },
        {
            "hora": "04,00",
            "precio": 0.11816
        },
        {
            "hora": "05,00",
            "precio": 0.11898
        },
        {
            "hora": "06,00",
            "precio": 0.12168000000000001
        },
        {
            "hora": "07,00",
            "precio": 0.11921
        },
        {
            "hora": "08,00",
            "precio": 0.07920999999999999
        },
        {
            "hora": "09,00",
            "precio": 0.04203
        },
        {
            "hora": "10,00",
            "precio": 0.04129
        },
        {
            "hora": "11,00",
            "precio": 0.04102
        },
        {
            "hora": "12,00",
            "precio": 0.04126
        },
        {
            "hora": "13,00",
            "precio": 0.04084
        },
        {
            "hora": "14,00",
            "precio": 0.04132
        },
        {
            "hora": "15,00",
            "precio": 0.04293
        },
        {
            "hora": "16,00",
            "precio": 0.0439
        },
        {
            "hora": "17,00",
            "precio": 0.039049999999999994
        },
        {
            "hora": "18,00",
            "precio": 0.03896
        },
        {
            "hora": "19,00",
            "precio": 0.06576
        },
        {
            "hora": "20,00",
            "precio": 0.12224
        },
        {
            "hora": "21,00",
            "precio": 0.15941999999999998
        },
        {
            "hora": "22,00",
            "precio": 0.1746
        },
        {
            "hora": "23,00",
            "precio": 0.16519999999999999
        }
    ]
}